[
  {
    "name": "org.apache.dubbo.spring.boot.autoconfigure.DubboRelaxedBinding2AutoConfiguration$$SpringCGLIB$$0",
    "allDeclaredFields": true,
    "allDeclaredConstructors": true,
    "allDeclaredMethods": true,
    "methods": [
      {
        "name": "<init>",
        "parameterTypes": [ ]
      }
    ]
  },
  {
    "name": "org.apache.dubbo.spring.boot.autoconfigure.DubboAutoConfiguration$$SpringCGLIB$$0",
    "allDeclaredFields": true,
    "allDeclaredConstructors": true,
    "allDeclaredMethods": true,
    "methods": [
      {
        "name": "<init>",
        "parameterTypes": [ ]
      }
    ]
  }
]